<?xml version="1.0" encoding="UTF-8" standalone="no"?>

<ui-command xmlns="http://www.efaps.org/xsd" xmlns:xsi="http://www.w3.org/2001/XMLSchema-instance"
    xsi:schemaLocation="http://www.efaps.org/xsd http://www.efaps.org/xsd/eFaps_1.0.xsd">

    <uuid>8071a2f1-1238-4a33-8dce-1ab87d8e8cd8</uuid>
    <file-application>eFapsApp-Accounting</file-application>
    

    <definition>
        <version-expression>(version==latest)</version-expression>
        <name>Accounting_PeriodTree_Menu_ActionExport_ExportAccountTable</name>

        <access>
            <role>Accounting_Admin</role>
            <role>Accounting_Manager</role>
        </access>

        

        <target>
            <execute program="org.efaps.esjp.accounting.export.ExportAccount" />
        </target>

        

        <property name="Target">hidden</property>
        <property name="TargetShowFile">true</property>
    </definition>

</ui-command>
