<?xml version="1.0" encoding="UTF-8" standalone="no"?>

<ui-menu xmlns="http://www.efaps.org/xsd" xmlns:xsi="http://www.w3.org/2001/XMLSchema-instance"
    xsi:schemaLocation="http://www.efaps.org/xsd http://www.efaps.org/xsd/eFaps_1.0.xsd">
    <uuid>70f83198-bc9a-477e-9603-db28462f574b</uuid>
    <file-application>eFapsApp-Accounting</file-application>
    
    <definition>
        <version-expression>(version==latest)</version-expression>
        <name>Accounting_ReportSubJournalTree</name>
        <target>
            <menu>Accounting_ReportSubJournalTree_Menu</menu>
            <form>Accounting_ReportSubJournalForm</form>
        </target>
        <type>Accounting_ReportSubJournal</type>
        <childs>
            <child>Accounting_ReportSubJournalTree_Transaction</child>
        </childs>
        <property name="Target">content</property>
        <property name="TargetMode">view</property>
    </definition>
</ui-menu>
