<?xml version="1.0" encoding="UTF-8" standalone="no"?>
<ui-menu xmlns="http://www.efaps.org/xsd" xmlns:xsi="http://www.w3.org/2001/XMLSchema-instance" xsi:schemaLocation="http://www.efaps.org/xsd http://www.efaps.org/xsd/eFaps_1.0.xsd">

    <uuid>4c21641d-f0c8-4f6a-8f8c-d886797e6433</uuid>
    <file-application>eFapsApp-Accounting</file-application>
    

    <definition>
        <version-expression>(version==latest)</version-expression>
        <name>Accounting_CaseTree_Report_Menu_Action</name>
        

        <childs>
            <child>Accounting_CaseTree_Report_Menu_Action_AddExisting</child>
            <child>Accounting_CaseTree_Report_Menu_Action_Disconnect</child>
        </childs>
    </definition>

</ui-menu>
