<?xml version="1.0" encoding="UTF-8"?>




<datamodel-type  xmlns="http://www.efaps.org/xsd"
                 xmlns:xsi="http://www.w3.org/2001/XMLSchema-instance"
                 xsi:schemaLocation="http://www.efaps.org/xsd http://www.efaps.org/xsd/eFaps_1.0.xsd">
    <uuid>f6f52802-c362-4e77-9068-ba02303f7b5c</uuid>
    <file-application>eFapsApp-Accounting</file-application>
    
    <specification>DM00038</specification>

    <definition>
        <version-expression>(version==latest)</version-expression>
        <name>Accounting_Account2CaseCredit</name>
        <parent>Accounting_Account2CaseAbstract</parent>
    </definition>
</datamodel-type>
