<?xml version="1.0" encoding="UTF-8"?>




<datamodel-type  xmlns="http://www.efaps.org/xsd"
                 xmlns:xsi="http://www.w3.org/2001/XMLSchema-instance"
                 xsi:schemaLocation="http://www.efaps.org/xsd http://www.efaps.org/xsd/eFaps_1.0.xsd">
    <uuid>aa0b85a3-e9ea-4aea-8870-1ff353647708</uuid>
    <file-application>eFapsApp-Accounting</file-application>
    
    <specification></specification>

    <definition>
        <version-expression>(version==latest)</version-expression>
        <name>Accounting_ReportAccount</name>
        <parent>Accounting_ReportSingularAbstract</parent>
        <trigger program="org.efaps.esjp.accounting.report.Report"
            method="deleteReportTrigger"
            name="Accounting_ReportAccount.DELETE_PRE"
            event="DELETE_PRE"/>
    </definition>
</datamodel-type>
