<?xml version="1.0" encoding="UTF-8"?>




<datamodel-statusgroup  xmlns="http://www.efaps.org/xsd"
                 xmlns:xsi="http://www.w3.org/2001/XMLSchema-instance"
                 xsi:schemaLocation="http://www.efaps.org/xsd http://www.efaps.org/xsd/eFaps_1.0.xsd">
    <uuid>1e95c195-f701-43e7-af90-7012779e18c9</uuid>
    <file-application>eFapsApp-Accounting</file-application>
    

    <definition>

        <version-expression>(version==latest)</version-expression>
        <name>Accounting_ExternalVoucherStatus</name>
        <parent>Accounting_DocumentStatus</parent>
        <status key="Open">
            <description>Invoice was printed, but needs to be payed for.
            </description>
        </status>
        <status key="Paid">
            <description>Invoice was payed.</description>
        </status>
        <status key="Booked">
            <description>Invoice was booked.</description>
        </status>
        <status key="Replaced">
            <description>Invoice was replaced by another Invoice or Receipt.</description>
        </status>
    </definition>
</datamodel-statusgroup>

